{
  "generator-jhipster": {
    "applicationType": "monolith",
    "gitCompany": "",
    "baseName": "jhipsterEmployeManage",
    "packageName": "com.gestionemployee",
    "packageFolder": "com/gestionemployee",
    "serverPort": 8080,
    "serviceDiscoveryType": false,
    "authenticationType": "jwt",
    "cacheProvider": "ehcache",
    "enableHibernateCache": true,
    "websocket": false,
    "databaseType": "sql",
    "devDatabaseType": "h2Disk",
    "prodDatabaseType": "mysql",
    "searchEngine": false,
    "enableSwaggerCodegen": false,
    "messageBroker": false,
    "buildTool": "maven",
    "useSass": true,
    "clientPackageManager": "npm",
    "testFrameworks": [],
    "enableTranslation": true,
    "nativeLanguage": "en",
    "languages": ["en", "fr"],
    "clientFramework": "angularX",
    "jhiPrefix": "jhi",
    "withAdminUi": true,
    "jhipsterVersion": "7.1.0",
    "skipClient": false,
    "skipServer": false,
    "skipUserManagement": false,
    "skipCheckLengthOfIdentifier": false,
    "skipFakeData": false,
    "entitySuffix": "",
    "dtoSuffix": "DTO",
    "blueprints": [],
    "otherModules": [],
    "pages": [],
    "creationTimestamp": 1631396997099,
    "jwtSecretKey": "OTVlZDYyNDIyZmY2OTUzZWRiYTg0MzM3MGFiNWNkNjZiM2ZjY2FmZTM4NzFlY2ZjYzg0MGU4Mjg0ZDBlZWJjMWIwODUwNTQ1MTBjNTU5OTYxMTU1MTQzNzgyYzdiMzdmYzA4MWEwNjcxODY4ODA2M2NlZmEwOTA0Y2M1ZDliNGM=",
    "devServerPort": 4200,
    "clientTheme": "none",
    "clientThemeVariant": "",
    "reactive": false,
    "entities": ["Region", "Country", "Location", "Department", "Task", "Employee", "Job", "JobHistory"],
    "lastLiquibaseTimestamp": 1631403341000
  },
  "git-provider": "GitHub",
  "git-company": "SOUGOU-Elhadji",
  "repository-name": "jhipster-gestion-employe"
}
